otdrs-1.1.1.dist-info/METADATA
otdrs-1.1.1.dist-info/WHEEL
otdrs-1.1.1.dist-info/licenses/LICENSE
otdrs/__init__.py
otdrs/__init__.pyi
otdrs/otdrs.abi3.so
otdrs/py.typed
otdrs-1.1.1.dist-info/RECORD
