Metadata-Version: 2.4
Name: otdrs
Version: 1.1.1
Classifier: Development Status :: 4 - Beta
Classifier: Programming Language :: Rust
Classifier: Topic :: File Formats
Classifier: License :: OSI Approved :: GNU Lesser General Public License v3 (LGPLv3)
Classifier: Programming Language :: Python :: Implementation :: CPython
Classifier: Programming Language :: Python :: Implementation :: PyPy
License-File: LICENSE
Summary: File parser and writer for optical time-domain reflectometry interchange files (Bellcore SOR)
Home-Page: https://github.com/JamesHarrison/otdrs
Requires-Python: >=3.7
